diffice_jax/__init__.py
diffice_jax/data/pinns/preprocessing.py
diffice_jax/data/pinns/sampling.py
diffice_jax/data/xpinns/preprocessing.py
diffice_jax/data/xpinns/sampling.py
diffice_jax/equation/eqn_aniso_zz.py
diffice_jax/equation/eqn_iso.py
diffice_jax/model/pinns/initialization.py
diffice_jax/model/pinns/loss.py
diffice_jax/model/pinns/networks.py
diffice_jax/model/pinns/prediction.py
diffice_jax/model/xpinns/initialization.py
diffice_jax/model/xpinns/loss.py
diffice_jax/model/xpinns/networks.py
diffice_jax/model/xpinns/prediction.py
diffice_jax/optimizer/optimization.py
diffice_jax-1.0.1.dist-info/licenses/LICENSE
docs/source/conf.py
diffice_jax-1.0.1.dist-info/METADATA
diffice_jax-1.0.1.dist-info/WHEEL
diffice_jax-1.0.1.dist-info/top_level.txt
diffice_jax-1.0.1.dist-info/RECORD
