Metadata-Version: 2.4
Name: DIFFICE_jax
Version: 1.0.1
Summary: A differentiable neural-network solver for data assimilation of ice shelves written in JAX
Author-email: Yongji Wang <yw8211@nyu.edu>, Ching-Yao Lai <cyaolai@stanford.edu>
Project-URL: Homepage, https://github.com/YaoGroup/DIFFICE_jax
Project-URL: Issues, https://github.com/YaoGroup/DIFFICE_jax/issues
Project-URL: repository, https://github.com/YaoGroup/DIFFICE_jax
Classifier: Programming Language :: Python :: 3
Classifier: License :: OSI Approved :: MIT License
Classifier: Operating System :: OS Independent
Requires-Python: >=3.9
License-File: LICENSE
Requires-Dist: jax>=0.4.20
Requires-Dist: jaxlib>=0.4.20
Requires-Dist: tensorflow-probability>=0.23.0
Requires-Dist: matplotlib>=3.8.0
Requires-Dist: optax>=0.1.7
Dynamic: license-file
